setup.py
Gaussian_and_Binomial_sethhamilton94/Binomialdistribution.py
Gaussian_and_Binomial_sethhamilton94/Gaussiandistribution.py
Gaussian_and_Binomial_sethhamilton94/Generaldistribution.py
Gaussian_and_Binomial_sethhamilton94/__init__.py
Gaussian_and_Binomial_sethhamilton94.egg-info/PKG-INFO
Gaussian_and_Binomial_sethhamilton94.egg-info/SOURCES.txt
Gaussian_and_Binomial_sethhamilton94.egg-info/dependency_links.txt
Gaussian_and_Binomial_sethhamilton94.egg-info/not-zip-safe
Gaussian_and_Binomial_sethhamilton94.egg-info/top_level.txt